sandtable_package_zend/__init__.py
sandtable_package_zend/functions.py
sandtable_package_zend/main.py
sandtable_package_zend/sender.py
vives_sandtable_package_zend-0.0.1.dist-info/LICENSE
vives_sandtable_package_zend-0.0.1.dist-info/METADATA
vives_sandtable_package_zend-0.0.1.dist-info/WHEEL
vives_sandtable_package_zend-0.0.1.dist-info/top_level.txt
vives_sandtable_package_zend-0.0.1.dist-info/RECORD
