Metadata-Version: 2.1
Name: vives-sandtable-package-zend
Version: 0.0.1
Summary: A package to drive the sand table.
Author-email: Bart Crul <bart.crul@student.vives.be>, Michiel Depraetere <michiel.depraetere@student.vives.be>, Gert De Craemere <gert.decreamere@student.vives.be>, Sirine Rajhi <sirine.rajhi@student.vives.be>
Project-URL: Homepage, https://github.com/vives-project-xp/Zend
Classifier: Programming Language :: Python :: 3
Classifier: License :: OSI Approved :: MIT License
Classifier: Operating System :: OS Independent
Requires-Python: >=3.7
License-File: LICENSE
